mscerts/__init__.py
mscerts/__main__.py
mscerts/authroot.stl
mscerts/cacert.pem
mscerts/core.py
mscerts/py.typed
mscerts-2025.6.27.dist-info/licenses/LICENSE
mscerts-2025.6.27.dist-info/METADATA
mscerts-2025.6.27.dist-info/WHEEL
mscerts-2025.6.27.dist-info/top_level.txt
mscerts-2025.6.27.dist-info/RECORD
