Metadata-Version: 2.4
Name: mscerts
Version: 2025.6.27
Summary: Python package for providing Microsoft's CA Bundle.
Home-page: https://github.com/ralphje/mscerts
Author: Ralph Broenink
Author-email: ralph@ralphbroenink.net
License: MPL-2.0
Project-URL: Source, https://github.com/ralphje/mscerts
Classifier: Development Status :: 5 - Production/Stable
Classifier: Intended Audience :: Developers
Classifier: License :: OSI Approved :: Mozilla Public License 2.0 (MPL 2.0)
Classifier: Natural Language :: English
Classifier: Programming Language :: Python
Classifier: Programming Language :: Python :: 3
Classifier: Programming Language :: Python :: 3 :: Only
Classifier: Programming Language :: Python :: 3.7
Classifier: Programming Language :: Python :: 3.8
Classifier: Programming Language :: Python :: 3.9
Classifier: Programming Language :: Python :: 3.10
Classifier: Programming Language :: Python :: 3.11
Classifier: Programming Language :: Python :: 3.12
Classifier: Programming Language :: Python :: 3.13
Requires-Python: >=3.7
License-File: LICENSE
Provides-Extra: stlupdate
Requires-Dist: requests; extra == "stlupdate"
Requires-Dist: signify; extra == "stlupdate"
Requires-Dist: asn1crypto; extra == "stlupdate"
Dynamic: author
Dynamic: author-email
Dynamic: classifier
Dynamic: description
Dynamic: home-page
Dynamic: license
Dynamic: license-file
Dynamic: project-url
Dynamic: provides-extra
Dynamic: requires-python
Dynamic: summary
